README.md
setup.py
jctestmod/__init__.py
jctestmod/text.py
jctestmod.egg-info/PKG-INFO
jctestmod.egg-info/SOURCES.txt
jctestmod.egg-info/dependency_links.txt
jctestmod.egg-info/not-zip-safe
jctestmod.egg-info/top_level.txt