Metadata-Version: 1.0
Name: jctestmod
Version: 0.2
Summary: Test wheel package mod
Home-page: http://github.com/storborg/funniest
Author: Juan Carlos
Author-email: jcmago@gmail.com
License: MIT
Platform: UNKNOWN
